aiodeluge/__init__.py
aiodeluge/client.py
aiodeluge/exception.py
aiodeluge/protocol.py
aiodeluge/request.py
aiodeluge-0.1.0.dist-info/METADATA
aiodeluge-0.1.0.dist-info/WHEEL
aiodeluge-0.1.0.dist-info/top_level.txt
aiodeluge-0.1.0.dist-info/RECORD
