Metadata-Version: 2.1
Name: aiodeluge
Version: 0.1.0
Summary: An asyncio client talk to deluged
Home-page: https://github.com/synodriver/aiodeluge
Author: synodriver
Author-email: diguohuangjiajinweijun@gmail.com
Maintainer: v-vinson
License: GPLv3
Keywords: asyncio,deluge
Platform: UNKNOWN
Classifier: Development Status :: 3 - Alpha
Classifier: Framework :: AsyncIO
Classifier: Operating System :: OS Independent
Classifier: License :: OSI Approved :: GNU General Public License v3 (GPLv3)
Classifier: Programming Language :: Python
Classifier: Programming Language :: Python :: 3.7
Classifier: Programming Language :: Python :: 3.8
Classifier: Programming Language :: Python :: 3.9
Classifier: Programming Language :: Python :: 3.10
Classifier: Programming Language :: Python :: 3.11
Classifier: Programming Language :: Python :: Implementation :: CPython
Requires-Python: >=3.6
Requires-Dist: rencode
Requires-Dist: loguru
